LangChainKaltura/KalturaCaptionLoader.py
LangChainKaltura/__init__.py
langchainkaltura-0.0.1.post1.dist-info/METADATA
langchainkaltura-0.0.1.post1.dist-info/WHEEL
langchainkaltura-0.0.1.post1.dist-info/licenses/LICENSE.txt
langchainkaltura-0.0.1.post1.dist-info/RECORD
