Metadata-Version: 2.3
Name: LangChainKaltura
Version: 0.0.1.post1
Summary: Collects captions from media in Kaltura and produces LangChain `Document` objects.
Project-URL: Homepage, https://github.com/umich-its-ai/langchain_kaltura
Project-URL: Issues, https://github.com/umich-its-ai/langchain_kaltura/issues
Author-email: "Mr. Lance E Sloan" <lsloan-github.com@umich.edu>
License-File: LICENSE.txt
Classifier: License :: OSI Approved :: GNU General Public License (GPL)
Classifier: Operating System :: OS Independent
Classifier: Programming Language :: Python :: 3
Requires-Python: >=3.11.8
